manifest/.DS_Store
manifest/__init__.py
manifest/admin.py
manifest/api_views.py
manifest/backends.py
manifest/context_processors.py
manifest/decorators.py
manifest/defaults.py
manifest/endpoints.py
manifest/forms.py
manifest/managers.py
manifest/messages.py
manifest/middlewares.py
manifest/mixins.py
manifest/models.py
manifest/serializers.py
manifest/signals.py
manifest/urls.py
manifest/utils.py
manifest/views.py
manifest/__pycache__/__init__.cpython-37.pyc
manifest/__pycache__/admin.cpython-37.pyc
manifest/__pycache__/api_views.cpython-37.pyc
manifest/__pycache__/backends.cpython-37.pyc
manifest/__pycache__/context_processors.cpython-37.pyc
manifest/__pycache__/decorators.cpython-37.pyc
manifest/__pycache__/defaults.cpython-37.pyc
manifest/__pycache__/endpoints.cpython-37.pyc
manifest/__pycache__/forms.cpython-37.pyc
manifest/__pycache__/managers.cpython-37.pyc
manifest/__pycache__/messages.cpython-37.pyc
manifest/__pycache__/middlewares.cpython-37.pyc
manifest/__pycache__/mixins.cpython-37.pyc
manifest/__pycache__/models.cpython-37.pyc
manifest/__pycache__/serializers.cpython-37.pyc
manifest/__pycache__/signals.cpython-37.pyc
manifest/__pycache__/templatetags.cpython-37.pyc
manifest/__pycache__/urls.cpython-37.pyc
manifest/__pycache__/utils.cpython-37.pyc
manifest/__pycache__/views.cpython-37.pyc
manifest/fixtures/test.json
manifest/locale/tr/LC_MESSAGES/django.po
manifest/management/__init__.py
manifest/management/__pycache__/__init__.cpython-37.pyc
manifest/management/commands/__init__.py
manifest/management/commands/clean_expired.py
manifest/management/commands/__pycache__/__init__.cpython-37.pyc
manifest/management/commands/__pycache__/clean_expired.cpython-37.pyc
manifest/management/project_templates/legacy/Pipfile
manifest/management/project_templates/legacy/manage.py
manifest/management/project_templates/legacy/project_name/__init__.py
manifest/management/project_templates/legacy/project_name/settings.py
django_manifest-0.2.1.dist-info/LICENCE
django_manifest-0.2.1.dist-info/METADATA
django_manifest-0.2.1.dist-info/WHEEL
django_manifest-0.2.1.dist-info/top_level.txt
django_manifest-0.2.1.dist-info/RECORD
